Workbook

Sheet README
A1: Dataset Dummy: Warung Selera Nusantara (Restoran)
A3: Sheet: transaksi -> 1 baris = 1 transaksi/struk (transaction_id unik)
A4: Sheet: transaksi_detail -> 1 baris = 1 menu dalam transaksi (1 transaksi bisa banyak menu)
A5: Sheet: menu -> master data menu, kategori, harga modal & jual
A6: Sheet: cabang -> master data cabang & kota
A8: Relasi: transaksi.transaction_id = transaksi_detail.transaction_id
A9: Relasi: transaksi_detail.menu_id = menu.menu_id
A10: Relasi: transaksi.cabang_id = cabang.cabang_id
A12: Catatan: ada data kotor sengaja (tipe_order huruf kapital tidak konsisten,
A13: spasi berlebih & 1 nilai kosong di metode_bayar, 1 baris duplikat di transaksi_detail)
A14: untuk latihan data cleaning.
A16: Periode data: Januari - Desember 2025
... A21: atau buat kolom bantu =HOUR(tanggal) di sheet transaksi.

Sheet transaksi
A1: transaction_id | B1: cabang_id | C1: tanggal | D1: tipe_order | E1: metode_bayar | F1: nama_hari | G1: nama_cabang
A2: TRX00813 | B2: CBG01 | C2: 45658.367 | D2: Dine-in | E2: QRIS | F2: =TEXT(C2,"dddd") -> Wednesday | G2: =VLOOKUP(B2,cabang!A:C,2,FALSE) -> Warung Selera Nusantara - Margonda
A3: TRX00188 | B3: CBG01 | C3: 45658.473 | D3: Dine-in | E3: QRIS | F3: =TEXT(C3,"dddd") -> Wednesday | G3: =VLOOKUP(B3,cabang!A:C,2,FALSE) -> Warung Selera Nusantara - Margonda
A4: TRX00146 | B4: CBG04 | C4: 45658.712 | D4: Take Away | E4: Cash | F4: =TEXT(C4,"dddd") -> Wednesday | G4: =VLOOKUP(B4,cabang!A:C,2,FALSE) -> Warung Selera Nusantara - Tunjungan
A5: TRX00385 | B5: CBG03 | C5: 45658.815 | D5: Take Away | E5: QRIS | F5: =TEXT(C5,"dddd") -> Wednesday | G5: =VLOOKUP(B5,cabang!A:C,2,FALSE) -> Warung Selera Nusantara - Sudirman
A6: TRX00149 | B6: CBG04 | C6: 45660.828 | D6: Dine-in | E6: E-wallet | F6: =TEXT(C6,"dddd") -> Friday | G6: =VLOOKUP(B6,cabang!A:C,2,FALSE) -> Warung Selera Nusantara - Tunjungan
A7: TRX00649 | B7: CBG03 | C7: 45660.833 | D7: Dine-in | E7: Cash | F7: =TEXT(C7,"dddd") -> Friday | G7: =VLOOKUP(B7,cabang!A:C,2,FALSE) -> Warung Selera Nusantara - Sudirman
A8: TRX00393 | B8: CBG03 | C8: 45661.394 | D8: Dine-in | E8: QRIS | F8: =TEXT(C8,"dddd") -> Saturday | G8: =VLOOKUP(B8,cabang!A:C,2,FALSE) -> Warung Selera Nusantara - Sudirman
A9: TRX00512 | B9: CBG01 | C9: 45661.556 | D9: Dine-in | E9: QRIS | F9: =TEXT(C9,"dddd") -> Saturday | G9: =VLOOKUP(B9,cabang!A:C,2,FALSE) -> Warung Selera Nusantara - Margonda
A10: TRX00243 | B10: CBG03 | C10: 45661.574 | D10: Take Away | E10: Kartu Debit/Kredit | F10: =TEXT(C10,"dddd") -> Saturday | G10: =VLOOKUP(B10,cabang!A:C,2,FALSE) -> Warung Selera Nusantara - Sudirman
A11: TRX00548 | B11: CBG03 | C11: 45662.672 | D11: Dine-in | E11: E-wallet | F11: =TEXT(C11,"dddd") -> Sunday | G11: =VLOOKUP(B11,cabang!A:C,2,FALSE) -> Warung Selera Nusantara - Sudirman
A12: TRX00382 | B12: CBG03 | C12: 45663.494 | D12: Dine-in | E12: QRIS | F12: =TEXT(C12,"dddd") -> Monday | G12: =VLOOKUP(B12,cabang!A:C,2,FALSE) -> Warung Selera Nusantara - Sudirman
A13: TRX00727 | B13: CBG01 | C13: 45663.511 | D13: Dine-in | E13: QRIS | F13: =TEXT(C13,"dddd") -> Monday | G13: =VLOOKUP(B13,cabang!A:C,2,FALSE) -> Warung Selera Nusantara - Margonda
... A563: TRX00068 | B563: CBG02 | C563: 45898.801 | D563: Take Away | E563: Kartu Debit/Kredit | F563: =TEXT(C563,"dddd") -> Friday | G563: =VLOOKUP(B563,cabang!A:C,2,FALSE) -> Warung Selera Nusantara - Dago
A564: TRX00546 | B564: CBG03 | C564: 45899.756 | D564: Dine-in | F564: =TEXT(C564,"dddd") -> Saturday | G564: =VLOOKUP(B564,cabang!A:C,2,FALSE) -> Warung Selera Nusantara - Sudirman
A565: TRX00342 | B565: CBG03 | C565: 45900.544 | D565: Dine-in | E565: E-wallet | F565: =TEXT(C565,"dddd") -> Sunday | G565: =VLOOKUP(B565,cabang!A:C,2,FALSE) -> Warung Selera Nusantara - Sudirman
A566: TRX00077 | B566: CBG03 | C566: 45900.557 | D566: Delivery | E566: QRIS | F566: =TEXT(C566,"dddd") -> Sunday | G566: =VLOOKUP(B566,cabang!A:C,2,FALSE) -> Warung Selera Nusantara - Sudirman
A567: TRX00328 | B567: CBG03 | C567: 45900.717 | D567: Dine-in | E567: QRIS | F567: =TEXT(C567,"dddd") -> Sunday | G567: =VLOOKUP(B567,cabang!A:C,2,FALSE) -> Warung Selera Nusantara - Sudirman
A568: TRX00508 | B568: CBG02 | C568: 45900.752 | D568: Dine-in | E568: QRIS | F568: =TEXT(C568,"dddd") -> Sunday | G568: =VLOOKUP(B568,cabang!A:C,2,FALSE) -> Warung Selera Nusantara - Dago
A569: TRX00265 | B569: CBG03 | C569: 45900.81 | D569: Dine-in | E569: E-wallet | F569: =TEXT(C569,"dddd") -> Sunday | G569: =VLOOKUP(B569,cabang!A:C,2,FALSE) -> Warung Selera Nusantara - Sudirman
A570: TRX00177 | B570: CBG04 | C570: 45900.853 | D570: Dine-in | E570: QRIS | F570: =TEXT(C570,"dddd") -> Sunday | G570: =VLOOKUP(B570,cabang!A:C,2,FALSE) -> Warung Selera Nusantara - Tunjungan
A571: TRX00472 | B571: CBG01 | C571: 45901.403 | D571: Delivery | E571: QRIS | F571: =TEXT(C571,"dddd") -> Monday | G571: =VLOOKUP(B571,cabang!A:C,2,FALSE) -> Warung Selera Nusantara - Margonda
A572: TRX00378 | B572: CBG04 | C572: 45901.583 | D572: Dine-in | E572: Kartu Debit/Kredit | F572: =TEXT(C572,"dddd") -> Monday | G572: =VLOOKUP(B572,cabang!A:C,2,FALSE) -> Warung Selera Nusantara - Tunjungan
A573: TRX00147 | B573: CBG03 | C573: 45901.82 | D573: Dine-in | E573: Kartu Debit/Kredit | F573: =TEXT(C573,"dddd") -> Monday | G573: =VLOOKUP(B573,cabang!A:C,2,FALSE) -> Warung Selera Nusantara - Sudirman
A574: TRX00710 | B574: CBG04 | C574: 45901.861 | D574: Dine-in | E574: Cash | F574: =TEXT(C574,"dddd") -> Monday | G574: =VLOOKUP(B574,cabang!A:C,2,FALSE) -> Warung Selera Nusantara - Tunjungan
A575: TRX00418 | B575: CBG02 | C575: 45902.504 | D575: Dine-in | E575: Cash | F575: =TEXT(C575,"dddd") -> Tuesday | G575: =VLOOKUP(B575,cabang!A:C,2,FALSE) -> Warung Selera Nusantara - Dago
A576: TRX00616 | B576: CBG01 | C576: 45902.558 | D576: Take Away | E576: Kartu Debit/Kredit | F576: =TEXT(C576,"dddd") -> Tuesday | G576: =VLOOKUP(B576,cabang!A:C,2,FALSE) -> Warung Selera Nusantara - Margonda
... A851: TRX00771 | B851: CBG02 | C851: 46022.576 | D851: Take Away | E851: E-wallet | F851: =TEXT(C851,"dddd") -> Wednesday | G851: =VLOOKUP(B851,cabang!A:C,2,FALSE) -> Warung Selera Nusantara - Dago

Sheet transaksi_detail
A1: detail_id | B1: transaction_id | C1: menu_id | D1: qty | E1: harga_satuan | F1: nama_menu | G1: revenue | H1: harga modal | I1: profit
A2: DTL00001 | B2: TRX00001 | C2: MNU016 | D2: 1 | E2: 18000 | F2: =VLOOKUP(C2,menu!A:B,2,FALSE) -> Es Kopi Susu Gula Aren | G2: =D2*E2 -> 18000 | H2: =VLOOKUP(C2,menu!A:E,4,FALSE) -> 4500 | I2: =(E2-H2)*D2 -> 13500
A3: DTL00002 | B3: TRX00001 | C3: MNU024 | D3: 1 | E3: 9000 | F3: =VLOOKUP(C3,menu!A:B,2,FALSE) -> Tempe Mendoan (5pcs) | G3: =D3*E3 -> 9000 | H3: =VLOOKUP(C3,menu!A:E,4,FALSE) -> 3000 | I3: =(E3-H3)*D3 -> 6000
A4: DTL00003 | B4: TRX00002 | C4: MNU019 | D4: 1 | E4: 5000 | F4: =VLOOKUP(C4,menu!A:B,2,FALSE) -> Air Mineral Botol | G4: =D4*E4 -> 5000 | H4: =VLOOKUP(C4,menu!A:E,4,FALSE) -> 2000 | I4: =(E4-H4)*D4 -> 3000
A5: DTL00004 | B5: TRX00002 | C5: MNU009 | D5: 1 | E5: 23000 | F5: =VLOOKUP(C5,menu!A:B,2,FALSE) -> Nasi Uduk Komplit | G5: =D5*E5 -> 23000 | H5: =VLOOKUP(C5,menu!A:E,4,FALSE) -> 9000 | I5: =(E5-H5)*D5 -> 14000
A6: DTL00005 | B6: TRX00002 | C6: MNU003 | D6: 1 | E6: 27000 | F6: =VLOOKUP(C6,menu!A:B,2,FALSE) -> Ayam Geprek Sambal Bawang | G6: =D6*E6 -> 27000 | H6: =VLOOKUP(C6,menu!A:E,4,FALSE) -> 11000 | I6: =(E6-H6)*D6 -> 16000
A7: DTL00006 | B7: TRX00002 | C7: MNU014 | D7: 1 | E7: 8000 | F7: =VLOOKUP(C7,menu!A:B,2,FALSE) -> Es Jeruk Peras | G7: =D7*E7 -> 8000 | H7: =VLOOKUP(C7,menu!A:E,4,FALSE) -> 2500 | I7: =(E7-H7)*D7 -> 5500
A8: DTL00007 | B8: TRX00002 | C8: MNU018 | D8: 1 | E8: 12000 | F8: =VLOOKUP(C8,menu!A:B,2,FALSE) -> Teh Tarik | G8: =D8*E8 -> 12000 | H8: =VLOOKUP(C8,menu!A:E,4,FALSE) -> 3000 | I8: =(E8-H8)*D8 -> 9000
A9: DTL00008 | B9: TRX00003 | C9: MNU010 | D9: 2 | E9: 22000 | F9: =VLOOKUP(C9,menu!A:B,2,FALSE) -> Pecel Lele | G9: =D9*E9 -> 44000 | H9: =VLOOKUP(C9,menu!A:E,4,FALSE) -> 9500 | I9: =(E9-H9)*D9 -> 25000
A10: DTL00009 | B10: TRX00003 | C10: MNU007 | D10: 1 | E10: 28000 | F10: =VLOOKUP(C10,menu!A:B,2,FALSE) -> Sate Ayam 10 Tusuk | G10: =D10*E10 -> 28000 | H10: =VLOOKUP(C10,menu!A:E,4,FALSE) -> 12000 | I10: =(E10-H10)*D10 -> 16000
A11: DTL00010 | B11: TRX00003 | C11: MNU017 | D11: 2 | E11: 16000 | F11: =VLOOKUP(C11,menu!A:B,2,FALSE) -> Jus Alpukat | G11: =D11*E11 -> 32000 | H11: =VLOOKUP(C11,menu!A:E,4,FALSE) -> 5500 | I11: =(E11-H11)*D11 -> 21000
A12: DTL00011 | B12: TRX00004 | C12: MNU018 | D12: 1 | E12: 12000 | F12: =VLOOKUP(C12,menu!A:B,2,FALSE) -> Teh Tarik | G12: =D12*E12 -> 12000 | H12: =VLOOKUP(C12,menu!A:E,4,FALSE) -> 3000 | I12: =(E12-H12)*D12 -> 9000
A13: DTL00012 | B13: TRX00004 | C13: MNU016 | D13: 1 | E13: 18000 | F13: =VLOOKUP(C13,menu!A:B,2,FALSE) -> Es Kopi Susu Gula Aren | G13: =D13*E13 -> 18000 | H13: =VLOOKUP(C13,menu!A:E,4,FALSE) -> 4500 | I13: =(E13-H13)*D13 -> 13500
... A2101: DTL01058 | B2101: TRX00426 | C2101: MNU021 | D2101: 1 | E2101: 10000 | F2101: =VLOOKUP(C2101,menu!A:B,2,FALSE) -> Tahu Isi Goreng (5pcs) | G2101: =D2101*E2101 -> 10000 | H2101: =VLOOKUP(C2101,menu!A:E,4,FALSE) -> 3500 | I2101: =(E2101-H2101)*D2101 -> 6500

Sheet menu
A1: menu_id | B1: nama_menu | C1: kategori | D1: harga_modal | E1: harga_jual
A2: MNU001 | B2: Nasi Goreng Spesial | C2: Makanan | D2: 9000 | E2: 25000
A3: MNU002 | B3: Mie Goreng Jawa | C3: Makanan | D3: 8500 | E3: 23000
A4: MNU003 | B4: Ayam Geprek Sambal Bawang | C4: Makanan | D4: 11000 | E4: 27000
A5: MNU004 | B5: Soto Ayam Lamongan | C5: Makanan | D5: 9500 | E5: 22000
A6: MNU005 | B6: Nasi Padang Rendang | C6: Makanan | D6: 14000 | E6: 32000
A7: MNU006 | B7: Gado-Gado Jakarta | C7: Makanan | D7: 8000 | E7: 20000
A8: MNU007 | B8: Sate Ayam 10 Tusuk | C8: Makanan | D8: 12000 | E8: 28000
A9: MNU008 | B9: Bakso Urat Spesial | C9: Makanan | D9: 8500 | E9: 21000
A10: MNU009 | B10: Nasi Uduk Komplit | C10: Makanan | D10: 9000 | E10: 23000
A11: MNU010 | B11: Pecel Lele | C11: Makanan | D11: 9500 | E11: 22000
A12: MNU011 | B12: Capcay Seafood | C12: Makanan | D12: 13000 | E12: 29000
A13: MNU012 | B13: Nasi Campur Bali | C13: Makanan | D13: 11500 | E13: 26000
... A25: MNU024 | B25: Tempe Mendoan (5pcs) | C25: Snack | D25: 3000 | E25: 9000

Sheet cabang
A1: cabang_id | B1: nama_cabang | C1: kota
A2: CBG01 | B2: Warung Selera Nusantara - Margonda | C2: Depok
A3: CBG02 | B3: Warung Selera Nusantara - Dago | C3: Bandung
A4: CBG03 | B4: Warung Selera Nusantara - Sudirman | C4: Jakarta
A5: CBG04 | B5: Warung Selera Nusantara - Tunjungan | C5: Surabaya

Sheet Pivot_Transaksi_per_Jam
A3: Row Labels | B3: Count of transaction_id
A4: 12 PM | B4: 117
A5: 7 PM | B5: 107
A6: 1 PM | B6: 89
A7: 6 PM | B7: 85
A8: 8 PM | B8: 77
A9: 11 AM | B9: 67
A10: 9 PM | B10: 50
A11: 5 PM | B11: 46
A12: 4 PM | B12: 37
A13: 2 PM | B13: 37
A14: 10 AM | B14: 35
A15: 8 AM | B15: 33
... A19: Grand Total | B19: 850

Sheet Pivot_Transaksi_per_Hari
A3: Row Labels | B3: Count of transaction_id
A4: Sunday | B4: 166
A5: Saturday | B5: 163
A6: Friday | B6: 115
A7: Wednesday | B7: 106
A8: Tuesday | B8: 106
A9: Monday | B9: 98
A10: Thursday | B10: 96
A11: Grand Total | B11: 850

Sheet Pivot_Transaksi_per_Cabang
A3: Row Labels | B3: Count of transaction_id
A4: Warung Selera Nusantara - Sudirman | B4: 303
A5: Warung Selera Nusantara - Tunjungan | B5: 206
A6: Warung Selera Nusantara - Margonda | B6: 179
A7: Warung Selera Nusantara - Dago | B7: 162
A8: Grand Total | B8: 850

Sheet Pivot_Qty_per_Menu
A3: Row Labels | B3: Sum of qty
A4: Ayam Geprek Sambal Bawang | B4: 694
A5: Es Kopi Susu Gula Aren | B5: 240
A6: Gado-Gado Jakarta | B6: 193
A7: Air Mineral Botol | B7: 166
A8: Nasi Uduk Komplit | B8: 162
A9: Nasi Campur Bali | B9: 161
A10: Jus Alpukat | B10: 135
A11: Tempe Mendoan (5pcs) | B11: 134
A12: Soto Ayam Lamongan | B12: 115
A13: Capcay Seafood | B13: 98
A14: Teh Tarik | B14: 90
A15: Kerupuk Udang | B15: 89
... A28: Grand Total | B28: 2784

Sheet Pivot_Revenue_per_Menu
A3: Row Labels | B3: Sum of revenue
A4: Ayam Geprek Sambal Bawang | B4: 18738000
A5: Es Kopi Susu Gula Aren | B5: 4320000
A6: Nasi Campur Bali | B6: 4186000
A7: Gado-Gado Jakarta | B7: 3860000
A8: Nasi Uduk Komplit | B8: 3726000
A9: Capcay Seafood | B9: 2842000
A10: Soto Ayam Lamongan | B10: 2530000
A11: Jus Alpukat | B11: 2160000
A12: Mie Goreng Jawa | B12: 1495000
A13: Tempe Mendoan (5pcs) | B13: 1206000
A14: Sate Ayam 10 Tusuk | B14: 1204000
A15: Es Campur | B15: 1200000
... A28: Grand Total | B28: 53854000

Sheet Pivot_Profit_per_Menu
A3: Row Labels | B3: Sum of profit
A4: Ayam Geprek Sambal Bawang | B4: 11104000
A5: Es Kopi Susu Gula Aren | B5: 3240000
A6: Nasi Campur Bali | B6: 2334500
A7: Gado-Gado Jakarta | B7: 2316000
A8: Nasi Uduk Komplit | B8: 2268000
A9: Capcay Seafood | B9: 1568000
A10: Soto Ayam Lamongan | B10: 1437500
A11: Jus Alpukat | B11: 1417500
A12: Mie Goreng Jawa | B12: 942500
A13: Teh Tarik | B13: 810000
A14: Tempe Mendoan (5pcs) | B14: 804000
A15: Es Campur | B15: 720000
... A28: Grand Total | B28: 33078500
